doxyplot/__init__.py
doxyplot/doxyplot_core.py
doxyplot/doxyplot_example.py
doxyplot/doxyplot_special_utils.py
doxyplot-0.1.0.dist-info/LICENSE
doxyplot-0.1.0.dist-info/METADATA
doxyplot-0.1.0.dist-info/WHEEL
doxyplot-0.1.0.dist-info/top_level.txt
doxyplot-0.1.0.dist-info/RECORD
