Metadata-Version: 2.1
Name: doxyplot
Version: 0.1.0
Summary: Doxyplot is a plotting wrapper around matplotlib for easy plotting.
Home-page: https://github.com/DovaX/doxyplot
Author: DovaX
Author-email: dovax.ai@gmail.com
License: UNKNOWN
Platform: UNKNOWN
Classifier: Programming Language :: Python :: 3
Classifier: License :: OSI Approved :: MIT License
Classifier: Operating System :: OS Independent
Requires-Python: >=3.6
Requires-Dist: matplotlib
